MANIFEST.in
README.md
setup.py
datareports/__init__.py
datareports/api.py
datareports/api_static.py
datareports/data_report.py
datareports/data_report_config.py
datareports/data_report_property.py
datareports/data_report_record.py
datareports/data_report_results.py
datareports/data_report_stats.py
datareports/db.py
datareports.egg-info/PKG-INFO
datareports.egg-info/SOURCES.txt
datareports.egg-info/dependency_links.txt
datareports.egg-info/requires.txt
datareports.egg-info/top_level.txt
datareports/templates/index.html
test/test.py