Metadata-Version: 1.0
Name: datareports
Version: 1.1.75
Summary: A python backend for jquery plugin datareports a wrapper for tablesorter. Including custom search,filter,sort and multi search
Home-page: https://github.com/chris17453/datareports/
Author: Charles Watkins
Author-email: charles@titandws.com
License: Creative Commons Attribution-Noncommercial-Share Alike license
Platform: UNKNOWN
